setup.py
search/__init__.py
search_python.egg-info/PKG-INFO
search_python.egg-info/SOURCES.txt
search_python.egg-info/dependency_links.txt
search_python.egg-info/requires.txt
search_python.egg-info/top_level.txt