Metadata-Version: 2.1
Name: search-python
Version: 1.0
Summary: A fast, efficiency python package for searching and getting search results with many different search engines.
Home-page: https://github.com/Neurs1/search
Author: Neurs
License: UNKNOWN
Platform: UNKNOWN
Classifier: Programming Language :: Python :: 3
Classifier: License :: OSI Approved :: MIT License
Classifier: Operating System :: OS Independent
Requires-Python: >3.0.0
